{
  "dimensions": {
    "趋势动能": 5.0,
    "资金质量": 9.0,
    "估值安全": 36.1,
    "基本面": 32.3,
    "周期位置": 33.0
  },
  "name": "海天味业",
  "ts_code": "603288.SH",
  "current_price": "32.98📅",
  "industry": "",
  "source": "8q",
  "_raw_summary": {
    "total": 30.5,
    "rating": "清仓离场",
    "comprehensive_rating": "强烈买入",
    "偏离度": 3.09,
    "目标价": "34.03",
    "2026E": 11.94,
    "ROE": 19.4904,
    "PE_TTM": 25.21
  },
  "current": "",
  "rating": "",
  "total": 0,
  "profit": 70.38,
  "roe": 19.49,
  "利润(亿)": 70.38,
  "ROE": 19.49,
  "stock_flow": 13793.29,
  "主力净流入(万元)": 13793.29,
  "tags": "高ROE,资金流入"
}