{
  "dimensions": {
    "趋势动能": 26.8,
    "资金质量": 3.8,
    "估值安全": 28.2,
    "基本面": 63.4,
    "周期位置": 36.0
  },
  "name": "寒武纪",
  "ts_code": "688256.SH",
  "current_price": "1458.00📅",
  "industry": "",
  "source": "8q",
  "_raw_summary": {
    "total": 59.0,
    "rating": "减持",
    "comprehensive_rating": "强烈买入",
    "偏离度": -1.15,
    "目标价": "1441.41",
    "2026E": 162.94,
    "ROE": 23.8629,
    "PE_TTM": 176.86
  },
  "current": "",
  "rating": "",
  "total": 0,
  "profit": 20.59,
  "roe": 23.86,
  "利润(亿)": 20.59,
  "ROE": 23.86,
  "stock_flow": 69219.78,
  "主力净流入(万元)": 69219.78,
  "tags": "高ROE,资金流入"
}